llama_index/packs/cogniswitch_agent/__init__.py
llama_index/packs/cogniswitch_agent/base.py
llama_index_packs_cogniswitch_agent-0.3.0.dist-info/METADATA
llama_index_packs_cogniswitch_agent-0.3.0.dist-info/WHEEL
llama_index_packs_cogniswitch_agent-0.3.0.dist-info/RECORD
