Metadata-Version: 2.1
Name: llama-index-packs-cogniswitch-agent
Version: 0.3.0
Summary: llama-index packs cogniswitch_agent integration
License: MIT
Keywords: embedding,graph,knowledge graph,neural,symbolic
Author: Your Name
Author-email: you@example.com
Maintainer: cogniswitch
Requires-Python: >=3.9,<4.0
Classifier: License :: OSI Approved :: MIT License
Classifier: Programming Language :: Python :: 3
Classifier: Programming Language :: Python :: 3.9
Classifier: Programming Language :: Python :: 3.10
Classifier: Programming Language :: Python :: 3.11
Classifier: Programming Language :: Python :: 3.12
Requires-Dist: llama-index-core (>=0.12.0,<0.13.0)
Requires-Dist: llama-index-tools-cogniswitch (>=0.3.0,<0.4.0)
